.gitignore
.readthedocs.yml
CHANGELOG.rst
LICENSE.txt
MANIFEST.in
README.rst
setup.cfg
setup.py
docs/Makefile
docs/avsc.rst
docs/colander.rst
docs/conf.py
docs/index.rst
docs/jsl.rst
docs/quickstart.rst
docs/sqla.rst
docs/toc.rst
inverter/__init__.py
inverter/common.py
inverter/dc2avsc.py
inverter/dc2colander.py
inverter/dc2colanderESjson.py
inverter/dc2colanderavro.py
inverter/dc2colanderjson.py
inverter/dc2esmapping.py
inverter/dc2jsl.py
inverter/dc2pgsqla.py
inverter/jsl2jsonobject.py
inverter/jsonobject2jsl.py
inverter.egg-info/PKG-INFO
inverter.egg-info/SOURCES.txt
inverter.egg-info/dependency_links.txt
inverter.egg-info/entry_points.txt
inverter.egg-info/not-zip-safe
inverter.egg-info/requires.txt
inverter.egg-info/top_level.txt