Metadata-Version: 1.1
Name: inverter
Version: 0.1.2
Summary: Convert dataclass to another class
Home-page: http://github.com/morpframework/inverter/
Author: Izhar Firdaus
Author-email: kagesenshi.87@gmail.com
License: Apache-2.0
Keywords: dataclass converter
Platform: UNKNOWN
Classifier: Development Status :: 4 - Beta
Classifier: License :: OSI Approved :: MIT License
Classifier: Topic :: Software Development :: Libraries :: Python Modules
